harmalysis/__init__.py
harmalysis/__main__.py
harmalysis/__version__.py
harmalysis/common.py
harmalysis/classes/__init__.py
harmalysis/classes/chord.py
harmalysis/classes/harmalysis.py
harmalysis/classes/interval.py
harmalysis/classes/key.py
harmalysis/classes/pitch_class.py
harmalysis/classes/scale.py
harmalysis/parsers/__init__.py
harmalysis/parsers/chordlabel.lark
harmalysis/parsers/chordlabel.py
harmalysis/parsers/roman.lark
harmalysis/parsers/roman.py
harmalysis/test/__init__.py
harmalysis/test/test_class.py
harmalysis-0.9.1.dist-info/LICENSE
harmalysis-0.9.1.dist-info/METADATA
harmalysis-0.9.1.dist-info/WHEEL
harmalysis-0.9.1.dist-info/top_level.txt
harmalysis-0.9.1.dist-info/RECORD
