Metadata-Version: 2.1
Name: harmalysis
Version: 0.9.1
Summary: A language for harmonic analysis and roman numerals.
Home-page: https://github.com/napulen/harmalysis
Author: Nestor Napoles Lopez
Author-email: napulen@gmail.com
License: GPLv3
Platform: UNKNOWN
Classifier: License :: OSI Approved :: GNU General Public License v3 (GPLv3)
Classifier: Programming Language :: Python
Classifier: Programming Language :: Python :: 3
Classifier: Programming Language :: Python :: 3.5
Classifier: Programming Language :: Python :: 3.6
Classifier: Programming Language :: Python :: Implementation :: CPython
Classifier: Programming Language :: Python :: Implementation :: PyPy
Requires-Python: >=3.5.0
Requires-Dist: lark-parser
